skyndo/_init_.py
skyndo/predict.py
skyndo-0.7.11.dist-info/METADATA
skyndo-0.7.11.dist-info/WHEEL
skyndo-0.7.11.dist-info/top_level.txt
skyndo-0.7.11.dist-info/RECORD
