Metadata-Version: 2.1
Name: skyndo
Version: 0.7.11
Summary: A package to predict the class of astronomical objects for given parameters using a Random Forest model
Home-page: https://github.com/NishanD21/Astronomical-Objects-Classification/tree/main/skyndo
Author: Nishan Obeyesekera
Author-email: nishandhanu21@gmail.com
License: UNKNOWN
Platform: UNKNOWN
Requires-Dist: pandas
Requires-Dist: scikit-learn
Requires-Dist: numpy
